repomap/__init__.py
repomap/cli.py
repomap/core.py
repomap/formatters/__init__.py
repomap/formatters/ascii.py
repomap/formatters/html.py
repomap/formatters/json.py
repomap/formatters/markdown.py
repodocify-1.0.0.dist-info/METADATA
repodocify-1.0.0.dist-info/WHEEL
repodocify-1.0.0.dist-info/entry_points.txt
repodocify-1.0.0.dist-info/RECORD
